Metadata-Version: 1.1
Name: dotconf
Version: 1.8
Summary: Advanced configuration parser for Python
Home-page: https://idevelop.org/p/dotconf/
Author: Antoine Millet
Author-email: antoine@inaps.org
License: MIT
Keywords: configuration parser dotconf conf
Platform: UNKNOWN
Classifier: Programming Language :: Python
Classifier: Programming Language :: Python :: 3
Classifier: Development Status :: 4 - Beta
Classifier: Intended Audience :: Developers
Classifier: License :: OSI Approved :: MIT License
Classifier: Operating System :: OS Independent
Classifier: Topic :: Software Development
Classifier: Topic :: Software Development :: Libraries
Classifier: Topic :: Text Processing
